dj/__init__.py
dj/cli.py
dj/constants.py
dj/exceptions.py
dj/inspect.py
dj/logging.py
dj/main.py
dj/registry/__init__.py
dj/registry/actor.py
dj/registry/config.py
dj/registry/journal.py
dj/registry/models.py
dj/registry/storage.py
dj/schemes.py
dj/utils.py
univocalx_dj-2.0.1.dist-info/METADATA
univocalx_dj-2.0.1.dist-info/WHEEL
univocalx_dj-2.0.1.dist-info/entry_points.txt
univocalx_dj-2.0.1.dist-info/licenses/LICENSE
univocalx_dj-2.0.1.dist-info/RECORD
