Metadata-Version: 2.4
Name: univocalx-dj
Version: 2.0.1
Summary: 
License-File: LICENSE
Author: elad jerbi
Author-email: eladxjerbi@gmail.com
Requires-Python: >=3.12
Classifier: Programming Language :: Python :: 3
Classifier: Programming Language :: Python :: 3.12
Classifier: Programming Language :: Python :: 3.13
Classifier: Programming Language :: Python :: 3.14
Requires-Dist: boto3 (>=1.39.16,<2.0.0)
Requires-Dist: psycopg2-binary (>=2.9.10,<3.0.0)
Requires-Dist: pydantic (>=2.11.7,<2.12.0)
Requires-Dist: pydantic-settings (>=2.10.1,<2.11.0)
Requires-Dist: python-magic (>=0.4.27,<0.5.0) ; sys_platform != "win32"
Requires-Dist: python-magic-bin (>=0.4.14,<0.5.0) ; sys_platform == "win32"
Requires-Dist: pyyaml (>=6.0.2,<7.0.0)
Requires-Dist: rich (>=14.2.0,<15.0.0)
Requires-Dist: sqlalchemy (>=2.0.42,<2.1.0)
Requires-Dist: tqdm (>=4.67.1,<5.0.0)
